pytest_nginx/__init__.py
pytest_nginx/factories.py
pytest_nginx/plugin.py
pytest_nginx-1.2.dist-info/licenses/LICENSE
pytest_nginx-1.2.dist-info/METADATA
pytest_nginx-1.2.dist-info/WHEEL
pytest_nginx-1.2.dist-info/entry_points.txt
pytest_nginx-1.2.dist-info/top_level.txt
pytest_nginx-1.2.dist-info/RECORD
