Metadata-Version: 2.4
Name: pytest-nginx
Version: 1.2
Summary: nginx fixture for pytest
Home-page: https://github.com/lahwaacz/pytest-nginx
Author: Jakub Klinkovský
Author-email: lahwaacz@users.noreply.github.com
License: GPLv3
Keywords: tests py.test pytest fixture nginx
Classifier: Development Status :: 5 - Production/Stable
Classifier: Environment :: Web Environment
Classifier: Intended Audience :: Developers
Classifier: License :: OSI Approved :: GNU General Public License v3 (GPLv3)
Classifier: Natural Language :: English
Classifier: Operating System :: OS Independent
Classifier: Programming Language :: Python
Classifier: Programming Language :: Python :: 3
Classifier: Topic :: Software Development :: Libraries :: Python Modules
License-File: LICENSE
Requires-Dist: pytest>=3.0.0
Dynamic: author
Dynamic: author-email
Dynamic: classifier
Dynamic: description
Dynamic: home-page
Dynamic: keywords
Dynamic: license
Dynamic: license-file
Dynamic: requires-dist
Dynamic: summary
